odoo/addons/purchase_all_shipments/README.rst
odoo/addons/purchase_all_shipments/__init__.py
odoo/addons/purchase_all_shipments/__manifest__.py
odoo/addons/purchase_all_shipments/i18n/es.po
odoo/addons/purchase_all_shipments/i18n/it.po
odoo/addons/purchase_all_shipments/i18n/pt_BR.po
odoo/addons/purchase_all_shipments/i18n/purchase_all_shipments.pot
odoo/addons/purchase_all_shipments/models/__init__.py
odoo/addons/purchase_all_shipments/models/purchase_order.py
odoo/addons/purchase_all_shipments/readme/CONTRIBUTORS.md
odoo/addons/purchase_all_shipments/readme/DESCRIPTION.md
odoo/addons/purchase_all_shipments/static/description/icon.png
odoo/addons/purchase_all_shipments/static/description/index.html
odoo/addons/purchase_all_shipments/tests/__init__.py
odoo/addons/purchase_all_shipments/tests/test_three_step_reception.py
odoo/addons/purchase_all_shipments/views/purchase_order_views.xml
odoo_addon_purchase_all_shipments-18.0.1.0.1.1.dist-info/METADATA
odoo_addon_purchase_all_shipments-18.0.1.0.1.1.dist-info/WHEEL
odoo_addon_purchase_all_shipments-18.0.1.0.1.1.dist-info/top_level.txt
odoo_addon_purchase_all_shipments-18.0.1.0.1.1.dist-info/RECORD
